Components/discrete/Transistors/kit/HomeDepot/CLB/mini_ethernet_phy/mini_ethernet_phy.vhd
library IEEE;
use IEEE.STD_LOGIC_1164.ALL;
use IEEE.NUMERIC_STD.ALL;

entity mini_ethernet_phy is
    port (
        clk         : in  std_logic;
        rst         : in  std_logic;
        din         : in  std_logic;
        payload_out : out std_logic_vector(3 downto 0);
        frame_ready : out std_logic
    );
end mini_ethernet_phy;

architecture rtl of mini_ethernet_phy is

    type state_type is (IDLE, PREAMBLE, SFD, PAYLOAD);
    signal state : state_type := IDLE;

    signal shift_reg  : std_logic_vector(7 downto 0) := (others => '0');
    signal byte_reg   : std_logic_vector(7 downto 0) := (others => '0');
    signal bit_cnt    : integer range 0 to 7 := 0;
    signal pre_cnt    : integer range 0 to 6 := 0;
    signal byte_valid : std_logic := '0';

begin

    process(clk)
    begin
        if rising_edge(clk) then
            if rst = '1' then
                shift_reg   <= (others => '0');
                byte_reg    <= (others => '0');
                bit_cnt     <= 0;
                pre_cnt     <= 0;
                state       <= IDLE;
                payload_out <= (others => '0');
                frame_ready <= '0';
                byte_valid  <= '0';

            else
                frame_ready <= '0';
                byte_valid  <= '0';

                -- Shift in serial bit (MSB first)
                shift_reg <= shift_reg(6 downto 0) & din;

                if bit_cnt = 7 then
                    bit_cnt    <= 0;
                    byte_reg   <= shift_reg(6 downto 0) & din;
                    byte_valid <= '1';
                else
                    bit_cnt <= bit_cnt + 1;
                end if;

                -- FSM consumes FULL BYTES only
                if byte_valid = '1' then
                    case state is
                        when IDLE =>
                            if byte_reg = "10101010" then
                                state   <= PREAMBLE;
                                pre_cnt <= 1;
                            end if;

                        when PREAMBLE =>
                            if byte_reg = "10101010" then
                                if pre_cnt = 6 then
                                    state <= SFD;
                                else
                                    pre_cnt <= pre_cnt + 1;
                                end if;
                            else
                                state   <= IDLE;
                                pre_cnt <= 0;
                            end if;

                        when SFD =>
                            if byte_reg = "10101011" then
                                state <= PAYLOAD;
                            else
                                state <= IDLE;
                            end if;

                        when PAYLOAD =>
                            payload_out <= byte_reg(3 downto 0);
                            frame_ready <= '1';
                            state <= IDLE;
                    end case;
                end if;
            end if;
        end if;
    end process;

end rtl;

Components/discrete/Transistors/74-series/HC/CLB/mini_ethernet_phy/tb_mini_ethernet_phy.vhd
library IEEE;
use IEEE.STD_LOGIC_1164.ALL;
use IEEE.NUMERIC_STD.ALL;
use std.env.all;

entity tb_mini_ethernet_phy is
end tb_mini_ethernet_phy;

architecture sim of tb_mini_ethernet_phy is

    signal clk         : std_logic := '0';
    signal rst         : std_logic := '1';
    signal din         : std_logic := '0';
    signal payload_out : std_logic_vector(3 downto 0);
    signal frame_ready : std_logic;

    constant CLK_PERIOD : time := 10 ns;

    -- Send byte MSB-first
    procedure send_byte(
        signal d : out std_logic;
        constant b : std_logic_vector(7 downto 0)
    ) is
    begin
        for i in 7 downto 0 loop
            d <= b(i);
            wait until rising_edge(clk);
        end loop;
    end procedure;

begin

    clk <= not clk after CLK_PERIOD/2;

    dut: entity work.mini_ethernet_phy
        port map (
            clk         => clk,
            rst         => rst,
            din         => din,
            payload_out => payload_out,
            frame_ready => frame_ready
        );

    stim: process
    begin
        -- reset
        wait for 30 ns;
        rst <= '0';

        -- 7x preamble
        for i in 1 to 7 loop
            send_byte(din, "10101010");
        end loop;

        -- SFD
        send_byte(din, "10101011");

        -- payload (1010xxxx)
        send_byte(din, "10100000");

        -- wait for frame_ready
        loop
            wait until rising_edge(clk);
            exit when frame_ready = '1';
        end loop;

        assert payload_out = "1010"
            report "ERROR: Payload mismatch"
            severity error;

        report "OK: Frame received correctly" severity note;
        stop;
    end process;

    watchdog: process
    begin
        wait for 5 us;
        assert false
            report "ERROR: Simulation timeout"
            severity failure;
    end process;

end sim;

Components/discrete/Transistors/kit/HomeDepot/CLB/mini_ethernet_phy/wave.vcd
$date
  Wed Dec 17 22:59:42 2025
$end
$version
  GHDL v0
$end
$timescale
  1 fs
$end
$scope module standard $end
$upscope $end
$scope module textio $end
$upscope $end
$scope module std_logic_1164 $end
$upscope $end
$scope module numeric_std $end
$upscope $end
$scope module env $end
$upscope $end
$scope module tb_mini_ethernet_phy $end
$var reg 1 ! clk $end
$var reg 1 " rst $end
$var reg 1 # din $end
$var reg 4 $ payload_out[3:0] $end
$var reg 1 % frame_ready $end
$scope module dut $end
$var reg 1 & clk $end
$var reg 1 ' rst $end
$var reg 1 ( din $end
$var reg 4 ) payload_out[3:0] $end
$var reg 1 * frame_ready $end
$comment state is not handled $end
$var reg 8 + shift_reg[7:0] $end
$var reg 8 , byte_reg[7:0] $end
$var integer 32 - bit_cnt $end
$var integer 32 . pre_cnt $end
$var reg 1 / byte_valid $end
$upscope $end
$upscope $end
$enddefinitions $end
#0
0!
1"
0#
bUUUU $
U%
0&
1'
0(
bUUUU )
U*
b00000000 +
b00000000 ,
b0 -
b0 .
0/
#5000000
1!
b0000 $
0%
1&
b0000 )
0*
#10000000
0!
0&
#15000000
1!
1&
#20000000
0!
0&
#25000000
1!
1&
#30000000
0!
0"
1#
0&
0'
1(
#35000000
1!
0#
1&
0(
b00000001 +
b1 -
#40000000
0!
0&
#45000000
1!
1#
1&
1(
b00000010 +
b10 -
#50000000
0!
0&
#55000000
1!
0#
1&
0(
b00000101 +
b11 -
#60000000
0!
0&
#65000000
1!
1#
1&
1(
b00001010 +
b100 -
#70000000
0!
0&
#75000000
1!
0#
1&
0(
b00010101 +
b101 -
#80000000
0!
0&
#85000000
1!
1#
1&
1(
b00101010 +
b110 -
#90000000
0!
0&
#95000000
1!
0#
1&
0(
b01010101 +
b111 -
#100000000
0!
0&
#105000000
1!
1#
1&
1(
b10101010 +
b10101010 ,
b0 -
1/
#110000000
0!
0&
#115000000
1!
0#
1&
0(
b01010101 +
b1 -
b1 .
0/
#120000000
0!
0&
#125000000
1!
1#
1&
1(
b10101010 +
b10 -
#130000000
0!
0&
#135000000
1!
0#
1&
0(
b01010101 +
b11 -
#140000000
0!
0&
#145000000
1!
1#
1&
1(
b10101010 +
b100 -
#150000000
0!
0&
#155000000
1!
0#
1&
0(
b01010101 +
b101 -
#160000000
0!
0&
#165000000
1!
1#
1&
1(
b10101010 +
b110 -
#170000000
0!
0&
#175000000
1!
0#
1&
0(
b01010101 +
b111 -
#180000000
0!
0&
#185000000
1!
1#
1&
1(
b10101010 +
b0 -
1/
#190000000
0!
0&
#195000000
1!
0#
1&
0(
b01010101 +
b1 -
b10 .
0/
#200000000
0!
0&
#205000000
1!
1#
1&
1(
b10101010 +
b10 -
#210000000
0!
0&
#215000000
1!
0#
1&
0(
b01010101 +
b11 -
#220000000
0!
0&
#225000000
1!
1#
1&
1(
b10101010 +
b100 -
#230000000
0!
0&
#235000000
1!
0#
1&
0(
b01010101 +
b101 -
#240000000
0!
0&
#245000000
1!
1#
1&
1(
b10101010 +
b110 -
#250000000
0!
0&
#255000000
1!
0#
1&
0(
b01010101 +
b111 -
#260000000
0!
0&
#265000000
1!
1#
1&
1(
b10101010 +
b0 -
1/
#270000000
0!
0&
#275000000
1!
0#
1&
0(
b01010101 +
b1 -
b11 .
0/
#280000000
0!
0&
#285000000
1!
1#
1&
1(
b10101010 +
b10 -
#290000000
0!
0&
#295000000
1!
0#
1&
0(
b01010101 +
b11 -
#300000000
0!
0&
#305000000
1!
1#
1&
1(
b10101010 +
b100 -
#310000000
0!
0&
#315000000
1!
0#
1&
0(
b01010101 +
b101 -
#320000000
0!
0&
#325000000
1!
1#
1&
1(
b10101010 +
b110 -
#330000000
0!
0&
#335000000
1!
0#
1&
0(
b01010101 +
b111 -
#340000000
0!
0&
#345000000
1!
1#
1&
1(
b10101010 +
b0 -
1/
#350000000
0!
0&
#355000000
1!
0#
1&
0(
b01010101 +
b1 -
b100 .
0/
#360000000
0!
0&
#365000000
1!
1#
1&
1(
b10101010 +
b10 -
#370000000
0!
0&
#375000000
1!
0#
1&
0(
b01010101 +
b11 -
#380000000
0!
0&
#385000000
1!
1#
1&
1(
b10101010 +
b100 -
#390000000
0!
0&
#395000000
1!
0#
1&
0(
b01010101 +
b101 -
#400000000
0!
0&
#405000000
1!
1#
1&
1(
b10101010 +
b110 -
#410000000
0!
0&
#415000000
1!
0#
1&
0(
b01010101 +
b111 -
#420000000
0!
0&
#425000000
1!
1#
1&
1(
b10101010 +
b0 -
1/
#430000000
0!
0&
#435000000
1!
0#
1&
0(
b01010101 +
b1 -
b101 .
0/
#440000000
0!
0&
#445000000
1!
1#
1&
1(
b10101010 +
b10 -
#450000000
0!
0&
#455000000
1!
0#
1&
0(
b01010101 +
b11 -
#460000000
0!
0&
#465000000
1!
1#
1&
1(
b10101010 +
b100 -
#470000000
0!
0&
#475000000
1!
0#
1&
0(
b01010101 +
b101 -
#480000000
0!
0&
#485000000
1!
1#
1&
1(
b10101010 +
b110 -
#490000000
0!
0&
#495000000
1!
0#
1&
0(
b01010101 +
b111 -
#500000000
0!
0&
#505000000
1!
1#
1&
1(
b10101010 +
b0 -
1/
#510000000
0!
0&
#515000000
1!
0#
1&
0(
b01010101 +
b1 -
b110 .
0/
#520000000
0!
0&
#525000000
1!
1#
1&
1(
b10101010 +
b10 -
#530000000
0!
0&
#535000000
1!
0#
1&
0(
b01010101 +
b11 -
#540000000
0!
0&
#545000000
1!
1#
1&
1(
b10101010 +
b100 -
#550000000
0!
0&
#555000000
1!
0#
1&
0(
b01010101 +
b101 -
#560000000
0!
0&
#565000000
1!
1#
1&
1(
b10101010 +
b110 -
#570000000
0!
0&
#575000000
1!
0#
1&
0(
b01010101 +
b111 -
#580000000
0!
0&
#585000000
1!
1#
1&
1(
b10101010 +
b0 -
1/
#590000000
0!
0&
#595000000
1!
0#
1&
0(
b01010101 +
b1 -
0/
#600000000
0!
0&
#605000000
1!
1#
1&
1(
b10101010 +
b10 -
#610000000
0!
0&
#615000000
1!
0#
1&
0(
b01010101 +
b11 -
#620000000
0!
0&
#625000000
1!
1#
1&
1(
b10101010 +
b100 -
#630000000
0!
0&
#635000000
1!
0#
1&
0(
b01010101 +
b101 -
#640000000
0!
0&
#645000000
1!
1#
1&
1(
b10101010 +
b110 -
#650000000
0!
0&
#655000000
1!
1&
b01010101 +
b111 -
#660000000
0!
0&
#665000000
1!
1&
b10101011 +
b10101011 ,
b0 -
1/
#670000000
0!
0&
#675000000
1!
0#
1&
0(
b01010111 +
b1 -
0/
#680000000
0!
0&
#685000000
1!
1#
1&
1(
b10101110 +
b10 -
#690000000
0!
0&
#695000000
1!
0#
1&
0(
b01011101 +
b11 -
#700000000
0!
0&
#705000000
1!
1&
b10111010 +
b100 -
#710000000
0!
0&
#715000000
1!
1&
b01110100 +
b101 -
#720000000
0!
0&
#725000000
1!
1&
b11101000 +
b110 -
#730000000
0!
0&
#735000000
1!
1&
b11010000 +
b111 -
#740000000
0!
0&
#745000000
1!
1&
b10100000 +
b10100000 ,
b0 -
1/
#750000000
0!
0&
#755000000
1!
1%
1&
1*
b01000000 +
b1 -
0/
