Components/discrete/Transistors/kit/HomeDepot/CLB/clb.vhd
library ieee;
use ieee.std_logic_1164.all;
use ieee.numeric_std.all;

-- ============================================================
-- CLB: Configurable Logic Block
-- FPGA-style CLB inspired by 74HC-based schematic
-- ============================================================

entity clb is
  port (
    -- External inputs
    in0     : in  std_logic;
    in1     : in  std_logic;
    in2     : in  std_logic;
    in3     : in  std_logic;

    -- Clocking
    clk     : in  std_logic;
    ce      : in  std_logic;

    -- Input select (74HC153 equivalent)
    sel0    : in  std_logic;
    sel1    : in  std_logic;

    -- Output select (74HC157 equivalent)
    regsel  : in  std_logic;  -- 0 = combinational, 1 = registered

    -- CLB output
    clb_out : out std_logic
  );
end entity clb;

-- ============================================================
-- RTL Architecture
-- ============================================================

architecture rtl of clb is

  -- Internal signals
  signal sel      : std_logic_vector(1 downto 0);
  signal lut_in   : std_logic;
  signal lut_out  : std_logic;
  signal reg_out  : std_logic;
  signal mux_out  : std_logic;

begin

  ----------------------------------------------------------------
  -- Input select vector (fixes GHDL overload issue)
  ----------------------------------------------------------------
  sel <= sel1 & sel0;

  ----------------------------------------------------------------
  -- Input MUX (74HC153 equivalent)
  ----------------------------------------------------------------
  with sel select
    lut_in <= in0 when "00",
              in1 when "01",
              in2 when "10",
              in3 when "11",
              '0' when others;

  ----------------------------------------------------------------
  -- LUT Logic (example combinational function)
  -- Replace this with any logic you want
  -- Example: (A XOR B) OR C
  ----------------------------------------------------------------
  lut_out <= (lut_in xor in1) or in2;

  ----------------------------------------------------------------
  -- D Flip-Flop (behavioral equivalent of NOR-based FF)
  -- Enabled clocked storage
  ----------------------------------------------------------------
  process(clk)
  begin
    if rising_edge(clk) then
      if ce = '1' then
        reg_out <= lut_out;
      end if;
    end if;
  end process;

  ----------------------------------------------------------------
  -- Output MUX (74HC157 equivalent)
  ----------------------------------------------------------------
  mux_out <= lut_out when regsel = '0' else reg_out;

  ----------------------------------------------------------------
  -- Output buffer (74HC125 / 74HC243 equivalent)
  ----------------------------------------------------------------
  clb_out <= mux_out;

end architecture rtl;

Components/discrete/Transistors/kit/HomeDepot/CLB/tb_clb.vhd
library ieee;
use ieee.std_logic_1164.all;
use ieee.numeric_std.all;

entity tb_clb is
end entity;

architecture sim of tb_clb is

  -- DUT signals
  signal in0     : std_logic := '0';
  signal in1     : std_logic := '0';
  signal in2     : std_logic := '0';
  signal in3     : std_logic := '0';

  signal clk     : std_logic := '0';
  signal ce      : std_logic := '0';

  signal sel0    : std_logic := '0';
  signal sel1    : std_logic := '0';
  signal regsel  : std_logic := '0';

  signal clb_out : std_logic;

  constant CLK_PERIOD : time := 10 ns;

begin

  ----------------------------------------------------------------
  -- Instantiate DUT
  ----------------------------------------------------------------
  uut: entity work.clb
    port map (
      in0     => in0,
      in1     => in1,
      in2     => in2,
      in3     => in3,
      clk     => clk,
      ce      => ce,
      sel0    => sel0,
      sel1    => sel1,
      regsel  => regsel,
      clb_out => clb_out
    );

  ----------------------------------------------------------------
  -- Clock generator
  ----------------------------------------------------------------
  clk_process : process
  begin
    while true loop
      clk <= '0';
      wait for CLK_PERIOD / 2;
      clk <= '1';
      wait for CLK_PERIOD / 2;
    end loop;
  end process;

  ----------------------------------------------------------------
  -- Stimulus process
  ----------------------------------------------------------------
  stim_proc : process
  begin
    --------------------------------------------------------------
    -- Initial state
    --------------------------------------------------------------
    ce     <= '0';
    regsel <= '0';
    sel1   <= '0';
    sel0   <= '0';

    in0 <= '0';
    in1 <= '0';
    in2 <= '0';
    in3 <= '0';

    wait for 20 ns;

    --------------------------------------------------------------
    -- Combinational mode
    --------------------------------------------------------------
    regsel <= '0';   -- combinational
    ce     <= '1';

    in0 <= '1';
    in1 <= '0';
    in2 <= '0';
    in3 <= '0';
    wait for 20 ns;

    sel0 <= '1';     -- select in1
    wait for 20 ns;

    sel1 <= '1';     -- select in3
    sel0 <= '1';
    in3  <= '1';
    wait for 20 ns;

    --------------------------------------------------------------
    -- Registered mode
    --------------------------------------------------------------
    regsel <= '1';   -- registered output
    ce     <= '1';

    sel1 <= '0';
    sel0 <= '0';
    in0  <= '0';
    in1  <= '1';
    in2  <= '1';

    wait for 30 ns;

    in1 <= '0';
    in2 <= '0';
    wait for 30 ns;

    --------------------------------------------------------------
    -- Disable clock enable
    --------------------------------------------------------------
    ce <= '0';
    in0 <= '1';
    wait for 30 ns;

    --------------------------------------------------------------
    -- End simulation
    --------------------------------------------------------------
    wait for 50 ns;
    assert false report "Simulation finished" severity failure;
  end process;

end architecture sim;

Components/discrete/Transistors/kit/HomeDepot/CLB/clb.vcd
$date
  Wed Dec 17 16:05:16 2025
$end
$version
  GHDL v0
$end
$timescale
  1 fs
$end
$scope module standard $end
$upscope $end
$scope module textio $end
$upscope $end
$scope module std_logic_1164 $end
$upscope $end
$scope module numeric_std $end
$upscope $end
$scope module tb_clb $end
$var reg 1 ! in0 $end
$var reg 1 " in1 $end
$var reg 1 # in2 $end
$var reg 1 $ in3 $end
$var reg 1 % clk $end
$var reg 1 & ce $end
$var reg 1 ' sel0 $end
$var reg 1 ( sel1 $end
$var reg 1 ) regsel $end
$var reg 1 * clb_out $end
$scope module uut $end
$var reg 1 + in0 $end
$var reg 1 , in1 $end
$var reg 1 - in2 $end
$var reg 1 . in3 $end
$var reg 1 / clk $end
$var reg 1 0 ce $end
$var reg 1 1 sel0 $end
$var reg 1 2 sel1 $end
$var reg 1 3 regsel $end
$var reg 1 4 clb_out $end
$var reg 2 5 sel[1:0] $end
$var reg 1 6 lut_in $end
$var reg 1 7 lut_out $end
$var reg 1 8 reg_out $end
$var reg 1 9 mux_out $end
$upscope $end
$upscope $end
$enddefinitions $end
#0
0!
0"
0#
0$
0%
0&
0'
0(
0)
0*
0+
0,
0-
0.
0/
00
01
02
03
04
b00 5
06
07
U8
09
#5000000
1%
1/
#10000000
0%
0/
#15000000
1%
1/
#20000000
1!
0%
1&
1*
1+
0/
10
14
16
17
19
#25000000
1%
1/
18
#30000000
0%
0/
#35000000
1%
1/
#40000000
0%
1'
0*
0/
11
04
b01 5
06
07
09
#45000000
1%
1/
08
#50000000
0%
0/
#55000000
1%
1/
#60000000
1$
0%
1(
1*
1.
0/
12
14
b11 5
16
17
19
#65000000
1%
1/
18
#70000000
0%
0/
#75000000
1%
1/
#80000000
0!
1"
1#
0%
0'
0(
1)
0+
1,
1-
0/
01
02
13
b00 5
06
#85000000
1%
1/
#90000000
0%
0/
#95000000
1%
1/
#100000000
0%
0/
#105000000
1%
1/
#110000000
0"
0#
0%
0,
0-
0/
07
#115000000
1%
0*
1/
04
08
09
#120000000
0%
0/
#125000000
1%
1/
#130000000
0%
0/
#135000000
1%
1/
#140000000
1!
0%
0&
1+
0/
00
16
17
